[
  {
    "name": "Dr. Elisabeth Dittrich",
    "profile_url": "https://www.docfinder.at/internist/1030-wien/dr-elisabeth-dittrich",
    "rating": "5,00",
    "reviews": "7",
    "specialty": "Internistin, Nephrologin",
    "address": "Mohsgasse 20/2, 1030 Wien",
    "services": "",
    "photo_url": "https://assets.docfinder.at/frontend/images/static/avatars/doctor_female.svg",
    "gallery": null,
    "appointment_url": null,
    "search_slug": "neuropathologe",
    "phone": "+43 680 2464486",
    "fax": null,
    "email": null,
    "website": null,
    "description": "Internistin, Nephrologin",
    "address_full": "Mohsgasse 20/2",
    "zip_code": "1030",
    "city": "Wien",
    "opening_hours": {
      "Wednesday": "14:00–19:00"
    },
    "latitude": "48.18949",
    "longitude": "16.387892",
    "photo_url_full": "https://assets.docfinder.at/frontend/images/static/avatars/doctor_female.svg"
  },
  {
    "name": "Prim. Dr. Heidemarie Abrahamian",
    "profile_url": "https://www.docfinder.at/internist/1040-wien/dr-heidemarie-abrahamian",
    "rating": "5,00",
    "reviews": "2",
    "specialty": "Internistin, Nephrologin, Endokrinologin, Intensivmedizinerin, Geriaterin",
    "address": "Prinz Eugen Straße 58 / Stock 4 / Top 21, 1040 Wien",
    "services": "",
    "photo_url": "https://assets.docfinder.at/frontend/images/static/avatars/doctor_female.svg",
    "gallery": null,
    "appointment_url": null,
    "search_slug": "neuropathologe",
    "phone": "+43 1 504 65 10",
    "fax": null,
    "email": null,
    "website": null,
    "description": "Internistin, Nephrologin, Endokrinologin, Intensivmedizinerin, Geriaterin",
    "address_full": "Prinz Eugen Straße 58 / Stock 4 / Top 21",
    "zip_code": "1040",
    "city": "Wien",
    "opening_hours": null,
    "latitude": "48.19098",
    "longitude": "16.37948",
    "photo_url_full": "https://assets.docfinder.at/frontend/images/static/avatars/doctor_female.svg"
  },
  {
    "name": "Dr. Astrid Ebner",
    "profile_url": "https://www.docfinder.at/internist/9020-klagenfurt/dr-astrid-ebner",
    "rating": "5,00",
    "reviews": "1",
    "specialty": "Internistin, Nephrologin",
    "address": "Lastenstraße 2, 9020 Klagenfurt",
    "services": "",
    "photo_url": "https://assets.docfinder.at/frontend/images/static/avatars/doctor_female.svg",
    "gallery": null,
    "appointment_url": null,
    "search_slug": "neuropathologe",
    "phone": " 0463 310 878",
    "fax": null,
    "email": null,
    "website": null,
    "description": "Internistin, Nephrologin",
    "address_full": "Lastenstraße 2",
    "zip_code": "9020",
    "city": "Klagenfurt",
    "opening_hours": {
      "Friday": "07:00–12:00",
      "Monday": "07:00–16:00",
      "Thursday": "07:00–13:00",
      "Tuesday": "07:00–13:00",
      "Wednesday": "07:00–16:00"
    },
    "latitude": "46.62022",
    "longitude": "14.31452",
    "photo_url_full": "https://assets.docfinder.at/frontend/images/static/avatars/doctor_female.svg"
  },
  {
    "name": "Dir. Dr. Brigitte Ettl-Karl",
    "profile_url": "https://www.docfinder.at/internist/1130-wien/dr-brigitte-ettl-karl",
    "rating": null,
    "reviews": null,
    "specialty": "Internistin, Nephrologin, Intensivmedizinerin, Endokrinologin",
    "address": "Hietzinger Hauptstraße 22, 1130 Wien",
    "services": "",
    "photo_url": "https://assets.docfinder.at/frontend/images/static/avatars/doctor_female.svg",
    "gallery": null,
    "appointment_url": null,
    "search_slug": "neuropathologe",
    "phone": "+43 664 300 82 63",
    "fax": null,
    "email": null,
    "website": null,
    "description": "Internistin, Nephrologin, Intensivmedizinerin, Endokrinologin",
    "address_full": "Hietzinger Hauptstraße 22",
    "zip_code": "1130",
    "city": "Wien",
    "opening_hours": {
      "Tuesday": "16:00–19:00"
    },
    "latitude": "48.186391",
    "longitude": "16.30022",
    "photo_url_full": "https://assets.docfinder.at/frontend/images/static/avatars/doctor_female.svg"
  },
  {
    "name": "Dr. Kurt Friedrich Possnig",
    "profile_url": "https://www.docfinder.at/internist/9020-klagenfurt/dr-kurt-friedrich-possnig",
    "rating": "3,67",
    "reviews": "6",
    "specialty": "Internist, Geriater, Nephrologe, Endokrinologe, Gastroenterologe u. Hepatologe, Hämatologe u. Onkologe",
    "address": "Feldkirchnerstraße 114, 9020 Klagenfurt",
    "services": "",
    "photo_url": "https://assets.docfinder.at/frontend/images/static/avatars/doctor.svg",
    "gallery": null,
    "appointment_url": null,
    "search_slug": "neuropathologe",
    "phone": "+43 463 420620",
    "fax": null,
    "email": null,
    "website": null,
    "description": "Internist, Geriater, Nephrologe, Endokrinologe, Gastroenterologe u. Hepatologe, Hämatologe u. Onkologe",
    "address_full": "Feldkirchnerstraße 114",
    "zip_code": "9020",
    "city": "Klagenfurt",
    "opening_hours": {
      "Friday": "08:00–10:00",
      "Monday": "08:00–13:00",
      "Thursday": "08:00–13:00",
      "Tuesday": "08:00–13:00",
      "Wednesday": "08:00–13:00, 16:00–19:00"
    },
    "latitude": "46.639962",
    "longitude": "14.29341",
    "photo_url_full": "https://assets.docfinder.at/frontend/images/static/avatars/doctor.svg"
  },
  {
    "name": "Dr. Thomas Grobner",
    "profile_url": "https://www.docfinder.at/internist/2700-wiener-neustadt/dr-thomas-grobner",
    "rating": "3,50",
    "reviews": "2",
    "specialty": "Internist, Nephrologe, Angiologe",
    "address": "Neuklosterplatz 1, 2700 Wiener Neustadt",
    "services": "",
    "photo_url": "https://assets.docfinder.at/frontend/images/static/avatars/doctor.svg",
    "gallery": null,
    "appointment_url": null,
    "search_slug": "neuropathologe",
    "phone": "+43 2622 25 864",
    "fax": null,
    "email": null,
    "website": null,
    "description": "Internist, Nephrologe, Angiologe",
    "address_full": "Neuklosterplatz 1",
    "zip_code": "2700",
    "city": "Wiener Neustadt",
    "opening_hours": null,
    "latitude": "47.812328",
    "longitude": "16.245907",
    "photo_url_full": "https://assets.docfinder.at/frontend/images/static/avatars/doctor.svg"
  },
  {
    "name": "Univ.Prof. Dr. Herwig Holzer",
    "profile_url": "https://www.docfinder.at/internist/8010-graz/dr-herwig-holzer",
    "rating": null,
    "reviews": null,
    "specialty": "Internist, Nephrologe",
    "address": "Elisabethstraße 54, 8010 Graz",
    "services": "",
    "photo_url": "https://assets.docfinder.at/frontend/images/static/avatars/doctor.svg",
    "gallery": null,
    "appointment_url": null,
    "search_slug": "neuropathologe",
    "phone": "+43 316 323 322-0",
    "fax": null,
    "email": null,
    "website": null,
    "description": "Internist, Nephrologe",
    "address_full": "Elisabethstraße 54",
    "zip_code": "8010",
    "city": "Graz",
    "opening_hours": {
      "Friday": "14:00–15:00, 15:00–20:00",
      "Monday": "18:00–20:00"
    },
    "latitude": "47.076078",
    "longitude": "15.456571",
    "photo_url_full": "https://assets.docfinder.at/frontend/images/static/avatars/doctor.svg"
  },
  {
    "name": "Priv. Doz. Dr. Katarzyna Krzyzanowska-Mittermayer, MBA",
    "profile_url": "https://www.docfinder.at/internist/1180-wien/dr-katarzyna-krzyzanowska-mittermayer-mba",
    "rating": "5,00",
    "reviews": "66",
    "specialty": "Internistin, Endokrinologin, Nephrologin",
    "address": "Kreuzgasse 17-19, 1180 Wien",
    "services": "Adipositas; Therapie von Schilddrüsenerkrankungen; Hormonelle Abklärungen und Therapieeinleitung bei endokrinologischen Fragestellungen; Strukturierte Betreuung bei Diabetes Mellitus (Beratung, medikamentöse Therapie inkl. Insulintherapien); Internistische Beratung und Therapie (Fettstoffwechselstörungen, Bluthochdruck, Nierenerkrankungen)",
    "photo_url": "https://images.docfinder.at/MUVDrJ_U8h/priv-doz-oae-dr-katarzyna-krzyzanowska-mittermayer-mba-5-61e.png",
    "gallery": [
      "https://images.docfinder.at/MUVDrJ_U8h/priv-doz-dr-katarzyna-krzyzanowska-mittermayer-mba-d3871.jpg",
      "https://images.docfinder.at/MUVDrJ_U8h/dr-katarzyna-krzyzanowska-mittermayer-internistin-1180-wien-6b531.jpg",
      "https://images.docfinder.at/MUVDrJ_U8h/priv-doz-dr-katarzyna-krzyzanowska-mittermayer-mba-b8670.jpg"
    ],
    "appointment_url": null,
    "search_slug": "neuropathologe",
    "phone": "+431261660",
    "fax": null,
    "email": "ordination@diabetes-1180.at",
    "website": "https://www.diabetes-1180.at/de/home",
    "description": "Internistin, Endokrinologin, Nephrologin",
    "address_full": "Kreuzgasse 17-19",
    "zip_code": "1180",
    "city": "Wien",
    "opening_hours": {
      "Thursday": "09:00–19:30",
      "Tuesday": "09:00–15:00",
      "Wednesday": "09:00–19:30"
    },
    "latitude": "48.22238",
    "longitude": "16.34084",
    "photo_url_full": "https://images.docfinder.at/MUVDrJ_U8h/priv-doz-oae-dr-katarzyna-krzyzanowska-mittermayer-mba-5-61e.png"
  },
  {
    "name": "Univ.Prof. Dr. Felix Stockenhuber",
    "profile_url": "https://www.docfinder.at/internist/1010-wien/dr-felix-stockenhuber",
    "rating": "2,75",
    "reviews": "122",
    "specialty": "Internist, Nephrologe, Intensivmediziner, Gastroenterologe u. Hepatologe",
    "address": "Naglergasse 11, 1010 Wien",
    "services": "Endoskopie; Gefäßerkrankungen; Schilddrüsenfehlfunktionen und Erkrankungen; Magen-Darm-Leber-Erkrankungen; Stoffwechselstörungen wie Diabetes; Bluthochdruck; Herzerkrankungen",
    "photo_url": "https://images.docfinder.at/A-mmZIsuhb/univ-prof-dr-felix-stockenhuber-454e1.jpg",
    "gallery": null,
    "appointment_url": null,
    "search_slug": "neuropathologe",
    "phone": "+43 1 535 46 57",
    "fax": null,
    "email": "office@praxisklinik.at",
    "website": "https://www.internist-stockenhuber.at/",
    "description": "Internist, Nephrologe, Intensivmediziner, Gastroenterologe u. Hepatologe",
    "address_full": "Naglergasse 11",
    "zip_code": "1010",
    "city": "Wien",
    "opening_hours": {
      "Friday": "09:00–13:00",
      "Monday": "08:30–19:00",
      "Thursday": "08:00–20:00",
      "Tuesday": "08:00–19:00",
      "Wednesday": "08:30–19:00"
    },
    "latitude": "48.210234",
    "longitude": "16.367416",
    "photo_url_full": "https://images.docfinder.at/A-mmZIsuhb/univ-prof-dr-felix-stockenhuber-454e1.jpg"
  },
  {
    "name": "OA Dr. Gerhard Christian Leitner",
    "profile_url": "https://www.docfinder.at/internist/8051-graz-goesting/dr-gerhard-christian-leitner",
    "rating": "5,00",
    "reviews": "2",
    "specialty": "Internist, Nephrologe",
    "address": "Fischeraustraße 13, 8051 Graz-Gösting",
    "services": "",
    "photo_url": "https://assets.docfinder.at/frontend/images/static/avatars/doctor.svg",
    "gallery": null,
    "appointment_url": null,
    "search_slug": "neuropathologe",
    "phone": "+43 316 67 10 77",
    "fax": null,
    "email": null,
    "website": null,
    "description": "Internist, Nephrologe",
    "address_full": "Fischeraustraße 13",
    "zip_code": "8051",
    "city": "Graz-Gösting",
    "opening_hours": {
      "Monday": "08:00–12:00"
    },
    "latitude": "47.094676",
    "longitude": "15.410136",
    "photo_url_full": "https://assets.docfinder.at/frontend/images/static/avatars/doctor.svg"
  },
  {
    "name": "OA Dr. Paul-Gerhard Peters",
    "profile_url": "https://www.docfinder.at/internist/6800-feldkirch/dr-paul-gerhard-peters",
    "rating": "5,00",
    "reviews": "1",
    "specialty": "Internist, Gastroenterologe u. Hepatologe, Nephrologe",
    "address": "Carinagasse 47, 6800 Feldkirch",
    "services": "",
    "photo_url": "https://assets.docfinder.at/frontend/images/static/avatars/doctor.svg",
    "gallery": null,
    "appointment_url": null,
    "search_slug": "neuropathologe",
    "phone": "+43 5522 303-2600",
    "fax": null,
    "email": null,
    "website": null,
    "description": "Internist, Gastroenterologe u. Hepatologe, Nephrologe",
    "address_full": "Carinagasse 47",
    "zip_code": "6800",
    "city": "Feldkirch",
    "opening_hours": null,
    "latitude": "47.231104",
    "longitude": "9.58008",
    "photo_url_full": "https://assets.docfinder.at/frontend/images/static/avatars/doctor.svg"
  },
  {
    "name": "Dr. Christoph Mayr",
    "profile_url": "https://www.docfinder.at/internist/6900-bregenz/dr-christoph-mayr",
    "rating": "5,00",
    "reviews": "2",
    "specialty": "Internist, Nephrologe",
    "address": "Bahnhofstraße 31/7, 6900 Bregenz",
    "services": "",
    "photo_url": "https://assets.docfinder.at/frontend/images/static/avatars/doctor.svg",
    "gallery": null,
    "appointment_url": null,
    "search_slug": "neuropathologe",
    "phone": "+43 5574 42982",
    "fax": null,
    "email": null,
    "website": null,
    "description": "Internist, Nephrologe",
    "address_full": "Bahnhofstraße 31/7",
    "zip_code": "6900",
    "city": "Bregenz",
    "opening_hours": {
      "Friday": "08:00–11:00",
      "Thursday": "08:00–12:00, 13:00–15:00",
      "Tuesday": "13:00–15:00, 08:00–11:30",
      "Wednesday": "08:00–11:30, 13:00–15:00"
    },
    "latitude": "47.50245",
    "longitude": "9.74178",
    "photo_url_full": "https://assets.docfinder.at/frontend/images/static/avatars/doctor.svg"
  },
  {
    "name": "Prim. Univ.Prof. Dr. Rudolf Prager",
    "profile_url": "https://www.docfinder.at/internist/1090-wien/dr-rudolf-prager",
    "rating": null,
    "reviews": null,
    "specialty": "Internist, Nephrologe, Endokrinologe",
    "address": "Pelikangasse 15/1, 1090 Wien",
    "services": "",
    "photo_url": "https://assets.docfinder.at/frontend/images/static/avatars/doctor.svg",
    "gallery": null,
    "appointment_url": null,
    "search_slug": "neuropathologe",
    "phone": "+43 1 40 180-1550",
    "fax": null,
    "email": null,
    "website": null,
    "description": "Internist, Nephrologe, Endokrinologe",
    "address_full": "Pelikangasse 15/1",
    "zip_code": "1090",
    "city": "Wien",
    "opening_hours": null,
    "latitude": "48.217074",
    "longitude": "16.348044",
    "photo_url_full": "https://assets.docfinder.at/frontend/images/static/avatars/doctor.svg"
  },
  {
    "name": "OA Dr. Rudolf Franz Huber",
    "profile_url": "https://www.docfinder.at/internist/5020-salzburg/dr-rudolf-franz-huber",
    "rating": null,
    "reviews": null,
    "specialty": "Internist, Kardiologe, Nephrologe, Gastroenterologe u. Hepatologe",
    "address": "Ginzkeyplatz 10/3, 5020 Salzburg",
    "services": "",
    "photo_url": "https://assets.docfinder.at/frontend/images/static/avatars/doctor.svg",
    "gallery": null,
    "appointment_url": null,
    "search_slug": "neuropathologe",
    "phone": "+43 650 620 65 03",
    "fax": null,
    "email": null,
    "website": null,
    "description": "Internist, Kardiologe, Nephrologe, Gastroenterologe u. Hepatologe",
    "address_full": "Ginzkeyplatz 10/3",
    "zip_code": "5020",
    "city": "Salzburg",
    "opening_hours": null,
    "latitude": "47.77295",
    "longitude": "13.070691",
    "photo_url_full": "https://assets.docfinder.at/frontend/images/static/avatars/doctor.svg"
  },
  {
    "name": "WHR Univ.Doz. Dr. Johann Pidlich, Ärztlicher Dir. Prim. em.",
    "profile_url": "https://www.docfinder.at/internist/2500-baden/dr-johann-pidlich",
    "rating": "5,00",
    "reviews": "3",
    "specialty": "Internist, Nephrologe, Gastroenterologe u. Hepatologe",
    "address": "Kaiser Franz-Ring 8/2, 2500 Baden",
    "services": "",
    "photo_url": "https://assets.docfinder.at/frontend/images/static/avatars/doctor.svg",
    "gallery": null,
    "appointment_url": null,
    "search_slug": "neuropathologe",
    "phone": "+43 2252 206090",
    "fax": null,
    "email": null,
    "website": null,
    "description": "Internist, Nephrologe, Gastroenterologe u. Hepatologe",
    "address_full": "Kaiser Franz-Ring 8/2",
    "zip_code": "2500",
    "city": "Baden",
    "opening_hours": {
      "Tuesday": "16:30–18:00"
    },
    "latitude": "48.009662",
    "longitude": "16.232839",
    "photo_url_full": "https://assets.docfinder.at/frontend/images/static/avatars/doctor.svg"
  },
  {
    "name": "Univ.Prof. Dr. Anton Luger",
    "profile_url": "https://www.docfinder.at/internist/1080-wien/dr-anton-luger",
    "rating": "5,00",
    "reviews": "3",
    "specialty": "Internist, Endokrinologe, Intensivmediziner, Nephrologe",
    "address": "Florianigasse 58/3, 1080 Wien",
    "services": "",
    "photo_url": "https://assets.docfinder.at/frontend/images/static/avatars/doctor.svg",
    "gallery": null,
    "appointment_url": null,
    "search_slug": "neuropathologe",
    "phone": "+43 1 4050408",
    "fax": null,
    "email": null,
    "website": null,
    "description": "Internist, Endokrinologe, Intensivmediziner, Nephrologe",
    "address_full": "Florianigasse 58/3",
    "zip_code": "1080",
    "city": "Wien",
    "opening_hours": null,
    "latitude": "48.212094",
    "longitude": "16.343464",
    "photo_url_full": "https://assets.docfinder.at/frontend/images/static/avatars/doctor.svg"
  },
  {
    "name": "OA Dr. Bernhard Robl",
    "profile_url": "https://www.docfinder.at/internist/4040-linz/dr-bernhard-robl",
    "rating": "5,00",
    "reviews": "1",
    "specialty": "Internist, Nephrologe",
    "address": "Rudolfstraße 8, 4040 Linz",
    "services": "",
    "photo_url": "https://assets.docfinder.at/frontend/images/static/avatars/doctor.svg",
    "gallery": null,
    "appointment_url": null,
    "search_slug": "neuropathologe",
    "phone": "+43 664 313 29 30",
    "fax": null,
    "email": null,
    "website": null,
    "description": "Internist, Nephrologe",
    "address_full": "Rudolfstraße 8",
    "zip_code": "4040",
    "city": "Linz",
    "opening_hours": {
      "Thursday": "16:00–20:00"
    },
    "latitude": "48.311094",
    "longitude": "14.28207",
    "photo_url_full": "https://assets.docfinder.at/frontend/images/static/avatars/doctor.svg"
  },
  {
    "name": "Univ.Doz. Dr. Harald E. Kotzmann",
    "profile_url": "https://www.docfinder.at/internist/1090-wien/dr-harald-e-kotzmann",
    "rating": "4,00",
    "reviews": "57",
    "specialty": "Internist, Kardiologe, Endokrinologe, Nephrologe",
    "address": "Schwarzspanierstraße 15/1, 1090 Wien",
    "services": "",
    "photo_url": "https://assets.docfinder.at/frontend/images/static/avatars/doctor.svg",
    "gallery": null,
    "appointment_url": null,
    "search_slug": "neuropathologe",
    "phone": "+43 1 4063688",
    "fax": null,
    "email": null,
    "website": null,
    "description": "Internist, Kardiologe, Endokrinologe, Nephrologe",
    "address_full": "Schwarzspanierstraße 15/1",
    "zip_code": "1090",
    "city": "Wien",
    "opening_hours": {
      "Friday": "09:00–12:00",
      "Monday": "11:30–16:30",
      "Thursday": "13:30–17:00, 10:00–11:30",
      "Tuesday": "13:30–17:00, 10:00–11:30",
      "Wednesday": "11:30–16:30"
    },
    "latitude": "48.216762",
    "longitude": "16.357465",
    "photo_url_full": "https://assets.docfinder.at/frontend/images/static/avatars/doctor.svg"
  },
  {
    "name": "Ass.-Prof. Univ.-Doz. Dr. Martin Haas, MSc",
    "profile_url": "https://www.docfinder.at/internist/2540-bad-voeslau/dr-martin-haas",
    "rating": null,
    "reviews": null,
    "specialty": "Internist, Kardiologe, Nephrologe, Intensivmediziner",
    "address": "Hanuschgasse 1/4/7, 2540 Bad Vöslau",
    "services": "Herzultraschall/Echokardiographie; Ergometrie/Belastungs - EKG; Langzeit-EKG/24-Stunden-EKG; Herzkatheter, Koronarangiographie (Ballondilatation, Stentimplantation); OP Freigabe und Begutachtung bei Niereninsuffizienz",
    "photo_url": "https://images.docfinder.at/zrO1B3bUaD/ass-prof-univ-doz-dr-martin-haas-msc-a8175.jpg",
    "gallery": null,
    "appointment_url": null,
    "search_slug": "neuropathologe",
    "phone": "+43 699-12543657",
    "fax": null,
    "email": null,
    "website": "https://www.kardiologie-haas.at/",
    "description": "Internist, Kardiologe, Nephrologe, Intensivmediziner",
    "address_full": "Hanuschgasse 1/4/7",
    "zip_code": "2540",
    "city": "Bad Vöslau",
    "opening_hours": {
      "Tuesday": "14:00–18:00"
    },
    "latitude": "47.96867",
    "longitude": "16.21971",
    "photo_url_full": "https://images.docfinder.at/zrO1B3bUaD/ass-prof-univ-doz-dr-martin-haas-msc-a8175.jpg"
  },
  {
    "name": "Prim. Univ.Doz. Dr. René Roland Wenzel",
    "profile_url": "https://www.docfinder.at/internist/5760-saalfelden-am-steinernen-meer/dr-rene-roland-wenzel",
    "rating": null,
    "reviews": null,
    "specialty": "Internist, Kardiologe, Nephrologe",
    "address": "Schalmenbergham 4, 5760 Saalfelden am Steinernen Meer",
    "services": "",
    "photo_url": "https://assets.docfinder.at/frontend/images/static/avatars/doctor.svg",
    "gallery": null,
    "appointment_url": null,
    "search_slug": "neuropathologe",
    "phone": "+43 6542 777",
    "fax": null,
    "email": null,
    "website": null,
    "description": "Internist, Kardiologe, Nephrologe",
    "address_full": "Schalmenbergham 4",
    "zip_code": "5760",
    "city": "Saalfelden am Steinernen Meer",
    "opening_hours": null,
    "latitude": "47.416612",
    "longitude": "12.850933",
    "photo_url_full": "https://assets.docfinder.at/frontend/images/static/avatars/doctor.svg"
  },
  {
    "name": "Prim.Priv.Doz. Dr. Marcus Säemann",
    "profile_url": "https://www.docfinder.at/internist/1080-wien/dr-marcus-saeemann",
    "rating": "5,00",
    "reviews": "5",
    "specialty": "Internist, Intensivmediziner, Nephrologe",
    "address": "Schmidgasse 16/1, 1080 Wien",
    "services": "",
    "photo_url": "https://assets.docfinder.at/frontend/images/static/avatars/doctor.svg",
    "gallery": null,
    "appointment_url": null,
    "search_slug": "neuropathologe",
    "phone": "+43 1 360 36-5900",
    "fax": null,
    "email": null,
    "website": null,
    "description": "Internist, Intensivmediziner, Nephrologe",
    "address_full": "Schmidgasse 16/1",
    "zip_code": "1080",
    "city": "Wien",
    "opening_hours": {
      "Tuesday": "15:00–20:00"
    },
    "latitude": "48.21054",
    "longitude": "16.35245",
    "photo_url_full": "https://assets.docfinder.at/frontend/images/static/avatars/doctor.svg"
  },
  {
    "name": "Ao.Univ.Prof. Dr. Bruno Watschinger",
    "profile_url": "https://www.docfinder.at/internist/1190-wien/dr-bruno-watschinger",
    "rating": null,
    "reviews": null,
    "specialty": "Internist, Nephrologe",
    "address": "Heiligenstädter Straße 57-63, 1190 Wien",
    "services": "",
    "photo_url": "https://assets.docfinder.at/frontend/images/static/avatars/doctor.svg",
    "gallery": null,
    "appointment_url": null,
    "search_slug": "neuropathologe",
    "phone": "+43 676 6423162",
    "fax": null,
    "email": null,
    "website": null,
    "description": "Internist, Nephrologe",
    "address_full": "Heiligenstädter Straße 57-63",
    "zip_code": "1190",
    "city": "Wien",
    "opening_hours": null,
    "latitude": "48.239107",
    "longitude": "16.358792",
    "photo_url_full": "https://assets.docfinder.at/frontend/images/static/avatars/doctor.svg"
  },
  {
    "name": "Prof. Dr. Gürkan Sengölge",
    "profile_url": "https://www.docfinder.at/internist/3003-gablitz/dr-guerkan-sengoelge",
    "rating": "5,00",
    "reviews": "10",
    "specialty": "Internist, Nephrologe",
    "address": "Kirchengasse 10, 3003 Gablitz",
    "services": "Proteinurie (Eiweiß im Harn); Ödeme; Nierenerkrankungen; Hämaturie (Blut im Harn); Systemerkrankungen mit Nierenbeteiligung; Hypertonie",
    "photo_url": "https://images.docfinder.at/Np2LYmdK3k/dr-guerkan-sengoelge-internist-3003-gablitz-5984b.jpg",
    "gallery": null,
    "appointment_url": null,
    "search_slug": "neuropathologe",
    "phone": "+43 650 8505899",
    "fax": null,
    "email": null,
    "website": null,
    "description": "Internist, Nephrologe",
    "address_full": "Kirchengasse 10",
    "zip_code": "3003",
    "city": "Gablitz",
    "opening_hours": null,
    "latitude": "48.227574",
    "longitude": "16.149834",
    "photo_url_full": "https://images.docfinder.at/Np2LYmdK3k/dr-guerkan-sengoelge-internist-3003-gablitz-5984b.jpg"
  },
  {
    "name": "Dr. Florian Fiedler",
    "profile_url": "https://www.docfinder.at/internist/3100-st-poelten/dr-florian-fiedler",
    "rating": "4,84",
    "reviews": "5",
    "specialty": "Internist, Endokrinologe, Kardiologe, Nephrologe",
    "address": "Grenzgasse 11/2, 3100 St. Pölten",
    "services": "",
    "photo_url": "https://assets.docfinder.at/frontend/images/static/avatars/doctor.svg",
    "gallery": null,
    "appointment_url": null,
    "search_slug": "neuropathologe",
    "phone": "+43 2742 35 28 87",
    "fax": null,
    "email": null,
    "website": null,
    "description": "Internist, Endokrinologe, Kardiologe, Nephrologe",
    "address_full": "Grenzgasse 11/2",
    "zip_code": "3100",
    "city": "St. Pölten",
    "opening_hours": {
      "Friday": "08:00–13:00",
      "Monday": "08:00–13:00",
      "Thursday": "08:00–13:00",
      "Tuesday": "08:00–13:00"
    },
    "latitude": "48.206558",
    "longitude": "15.624887",
    "photo_url_full": "https://assets.docfinder.at/frontend/images/static/avatars/doctor.svg"
  },
  {
    "name": "Dr. Michael Lanik",
    "profile_url": "https://www.docfinder.at/internist/1010-wien/dr-michael-lanik",
    "rating": "5,00",
    "reviews": "2",
    "specialty": "Internist, Nephrologe, Kardiologe, Angiologe",
    "address": "Opernring 4/2/6, 1010 Wien",
    "services": "",
    "photo_url": "https://assets.docfinder.at/frontend/images/static/avatars/doctor.svg",
    "gallery": null,
    "appointment_url": null,
    "search_slug": "neuropathologe",
    "phone": "+43 670 6041188",
    "fax": null,
    "email": null,
    "website": null,
    "description": "Internist, Nephrologe, Kardiologe, Angiologe",
    "address_full": "Opernring 4/2/6",
    "zip_code": "1010",
    "city": "Wien",
    "opening_hours": null,
    "latitude": "48.203094",
    "longitude": "16.367787",
    "photo_url_full": "https://assets.docfinder.at/frontend/images/static/avatars/doctor.svg"
  },
  {
    "name": "OA Dr. Peter Eichhorn",
    "profile_url": "https://www.docfinder.at/internist/3300-amstetten/dr-peter-eichhorn",
    "rating": null,
    "reviews": null,
    "specialty": "Internist, Nephrologe, Intensivmediziner, Gastroenterologe u. Hepatologe",
    "address": "Krankenhausstraße 21, 3300 Amstetten",
    "services": "",
    "photo_url": "https://assets.docfinder.at/frontend/images/static/avatars/doctor.svg",
    "gallery": null,
    "appointment_url": null,
    "search_slug": "neuropathologe",
    "phone": "+43 7472 604 80 14",
    "fax": null,
    "email": null,
    "website": null,
    "description": "Internist, Nephrologe, Intensivmediziner, Gastroenterologe u. Hepatologe",
    "address_full": "Krankenhausstraße 21",
    "zip_code": "3300",
    "city": "Amstetten",
    "opening_hours": {
      "Wednesday": "15:00–18:00"
    },
    "latitude": "48.127672",
    "longitude": "14.881958",
    "photo_url_full": "https://assets.docfinder.at/frontend/images/static/avatars/doctor.svg"
  },
  {
    "name": "Assoc.Prof.Priv.Doz.Dr. Zeljko Kikic",
    "profile_url": "https://www.docfinder.at/internist/1180-wien/dr-zeljko-kikic",
    "rating": "4,71",
    "reviews": "7",
    "specialty": "Internist, Nephrologe, Intensivmediziner",
    "address": "Kreuzgasse 17-19, 1180 Wien",
    "services": "",
    "photo_url": "https://images.docfinder.at/GurbP15hmK/assoc-prof-priv-doz-dr-zeljko-kikic-3f07.jpg",
    "gallery": null,
    "appointment_url": null,
    "search_slug": "neuropathologe",
    "phone": "+43 1 470 61 44",
    "fax": null,
    "email": "office@shariat.at",
    "website": "https://www.drkikic-internist.at/",
    "description": "Internist, Nephrologe, Intensivmediziner",
    "address_full": "Kreuzgasse 17-19",
    "zip_code": "1180",
    "city": "Wien",
    "opening_hours": null,
    "latitude": "48.22238",
    "longitude": "16.34084",
    "photo_url_full": "https://images.docfinder.at/GurbP15hmK/assoc-prof-priv-doz-dr-zeljko-kikic-3f07.jpg"
  },
  {
    "name": "Dr. Oliver Paul",
    "profile_url": "https://www.docfinder.at/internist/2630-ternitz/dr-oliver-paul",
    "rating": "2,77",
    "reviews": "14",
    "specialty": "Internist, Kardiologe, Nephrologe",
    "address": "Rathausgasse 8, 2630 Ternitz",
    "services": "",
    "photo_url": "https://assets.docfinder.at/frontend/images/static/avatars/doctor.svg",
    "gallery": null,
    "appointment_url": null,
    "search_slug": "neuropathologe",
    "phone": "+43 2630 369 10",
    "fax": null,
    "email": null,
    "website": null,
    "description": "Internist, Kardiologe, Nephrologe",
    "address_full": "Rathausgasse 8",
    "zip_code": "2630",
    "city": "Ternitz",
    "opening_hours": {
      "Monday": "09:00–13:00, 14:00–15:00, 15:00–16:00",
      "Thursday": "09:00–13:00",
      "Tuesday": "16:00–18:00, 09:00–13:00",
      "Wednesday": "09:00–13:00"
    },
    "latitude": "47.715698",
    "longitude": "16.038921",
    "photo_url_full": "https://assets.docfinder.at/frontend/images/static/avatars/doctor.svg"
  },
  {
    "name": "Univ.Prof. Dr. Martin Clodi",
    "profile_url": "https://www.docfinder.at/internist/1090-wien/dr-martin-clodi",
    "rating": "5,00",
    "reviews": "1",
    "specialty": "Internist, Endokrinologe, Intensivmediziner, Nephrologe, Geriater",
    "address": "Lazarettgasse 25/1.Stock, 1090 Wien",
    "services": "",
    "photo_url": "https://assets.docfinder.at/frontend/images/static/avatars/doctor.svg",
    "gallery": null,
    "appointment_url": null,
    "search_slug": "neuropathologe",
    "phone": "+43 1 401807010",
    "fax": null,
    "email": null,
    "website": null,
    "description": "Internist, Endokrinologe, Intensivmediziner, Nephrologe, Geriater",
    "address_full": "Lazarettgasse 25/1.Stock",
    "zip_code": "1090",
    "city": "Wien",
    "opening_hours": {
      "Tuesday": "16:00–20:00"
    },
    "latitude": "48.217064",
    "longitude": "16.346888",
    "photo_url_full": "https://assets.docfinder.at/frontend/images/static/avatars/doctor.svg"
  },
  {
    "name": "Dr. Christian Moser",
    "profile_url": "https://www.docfinder.at/internist/1010-wien/dr-christian-moser",
    "rating": "5,00",
    "reviews": "1",
    "specialty": "Internist, Nephrologe",
    "address": "Tuchlauben 17/1/8a, 1010 Wien",
    "services": "",
    "photo_url": "https://assets.docfinder.at/frontend/images/static/avatars/doctor.svg",
    "gallery": null,
    "appointment_url": null,
    "search_slug": "neuropathologe",
    "phone": "+43 1 8904122",
    "fax": null,
    "email": null,
    "website": null,
    "description": "Internist, Nephrologe",
    "address_full": "Tuchlauben 17/1/8a",
    "zip_code": "1010",
    "city": "Wien",
    "opening_hours": null,
    "latitude": "48.210677",
    "longitude": "16.371063",
    "photo_url_full": "https://assets.docfinder.at/frontend/images/static/avatars/doctor.svg"
  },
  {
    "name": "Dr. Gerhard Mitter",
    "profile_url": "https://www.docfinder.at/internist/4020-linz/dr-gerhard-mitter",
    "rating": "3,13",
    "reviews": "3",
    "specialty": "Internist, Nephrologe",
    "address": "Mozartstraße 6-10/4, 4020 Linz",
    "services": "",
    "photo_url": "https://assets.docfinder.at/frontend/images/static/avatars/doctor.svg",
    "gallery": null,
    "appointment_url": null,
    "search_slug": "neuropathologe",
    "phone": "+43 732 773546",
    "fax": null,
    "email": null,
    "website": null,
    "description": "Internist, Nephrologe",
    "address_full": "Mozartstraße 6-10/4",
    "zip_code": "4020",
    "city": "Linz",
    "opening_hours": {
      "Friday": "07:00–10:00",
      "Monday": "08:00–12:00",
      "Thursday": "08:00–12:00, 15:00–19:00",
      "Tuesday": "08:00–12:00, 14:00–17:00",
      "Wednesday": "08:00–13:00"
    },
    "latitude": "48.300999",
    "longitude": "14.291675",
    "photo_url_full": "https://assets.docfinder.at/frontend/images/static/avatars/doctor.svg"
  },
  {
    "name": "OA Doz. Dr. Gerfried Gratze",
    "profile_url": "https://www.docfinder.at/internist/8043-graz/dr-gerfried-gratze",
    "rating": null,
    "reviews": null,
    "specialty": "Internist, Nephrologe, Kardiologe, Geriater",
    "address": "Stattegger Straße 10, 8043 Graz",
    "services": "",
    "photo_url": "https://assets.docfinder.at/frontend/images/static/avatars/doctor.svg",
    "gallery": null,
    "appointment_url": null,
    "search_slug": "neuropathologe",
    "phone": "+43 316   69 23 740",
    "fax": null,
    "email": null,
    "website": null,
    "description": "Internist, Nephrologe, Kardiologe, Geriater",
    "address_full": "Stattegger Straße 10",
    "zip_code": "8043",
    "city": "Graz",
    "opening_hours": null,
    "latitude": "47.10734",
    "longitude": "15.42222",
    "photo_url_full": "https://assets.docfinder.at/frontend/images/static/avatars/doctor.svg"
  },
  {
    "name": "OA Dr. Martin Gerke",
    "profile_url": "https://www.docfinder.at/internist/5026-salzburg/dr-martin-gerke",
    "rating": "5,00",
    "reviews": "3",
    "specialty": "Internist, Nephrologe",
    "address": "Guggenbichlerstraße 20, 5026 Salzburg",
    "services": "",
    "photo_url": "https://assets.docfinder.at/frontend/images/static/avatars/doctor.svg",
    "gallery": null,
    "appointment_url": null,
    "search_slug": "neuropathologe",
    "phone": "+43 662 905 09  270",
    "fax": null,
    "email": null,
    "website": null,
    "description": "Internist, Nephrologe",
    "address_full": "Guggenbichlerstraße 20",
    "zip_code": "5026",
    "city": "Salzburg",
    "opening_hours": null,
    "latitude": "47.788191",
    "longitude": "13.07633",
    "photo_url_full": "https://assets.docfinder.at/frontend/images/static/avatars/doctor.svg"
  },
  {
    "name": "Dr. Michael Erath",
    "profile_url": "https://www.docfinder.at/internist/9500-villach/dr-michael-erath",
    "rating": "4,73",
    "reviews": "16",
    "specialty": "Internist, Nephrologe, Gastroenterologe u. Hepatologe",
    "address": "Ringmauergasse 10/4, 9500 Villach",
    "services": "",
    "photo_url": "https://assets.docfinder.at/frontend/images/static/avatars/doctor.svg",
    "gallery": null,
    "appointment_url": null,
    "search_slug": "neuropathologe",
    "phone": "+43 4242 225 01",
    "fax": null,
    "email": null,
    "website": null,
    "description": "Internist, Nephrologe, Gastroenterologe u. Hepatologe",
    "address_full": "Ringmauergasse 10/4",
    "zip_code": "9500",
    "city": "Villach",
    "opening_hours": {
      "Friday": "07:30–12:00",
      "Monday": "07:30–12:00",
      "Thursday": "07:30–12:00",
      "Tuesday": "07:30–12:00",
      "Wednesday": "07:30–12:00"
    },
    "latitude": "46.613759",
    "longitude": "13.843327",
    "photo_url_full": "https://assets.docfinder.at/frontend/images/static/avatars/doctor.svg"
  },
  {
    "name": "OA Dr. Wolfgang Pronai",
    "profile_url": "https://www.docfinder.at/internist/7000-eisenstadt/dr-wolfgang-pronai",
    "rating": null,
    "reviews": null,
    "specialty": "Internist, Nephrologe",
    "address": "Axerweg 42, 7000 Eisenstadt",
    "services": "",
    "photo_url": "https://assets.docfinder.at/frontend/images/static/avatars/doctor.svg",
    "gallery": null,
    "appointment_url": null,
    "search_slug": "neuropathologe",
    "phone": "+43 2682 647 30",
    "fax": null,
    "email": null,
    "website": null,
    "description": "Internist, Nephrologe",
    "address_full": "Axerweg 42",
    "zip_code": "7000",
    "city": "Eisenstadt",
    "opening_hours": null,
    "latitude": "47.847241",
    "longitude": "16.507693",
    "photo_url_full": "https://assets.docfinder.at/frontend/images/static/avatars/doctor.svg"
  },
  {
    "name": "Univ.Doz. Dr. Manfred Schmidbauer",
    "profile_url": "https://www.docfinder.at/neurologe/1130-wien/dr-manfred-schmidbauer",
    "rating": null,
    "reviews": null,
    "specialty": "Neurologe, Neuropathologe, Intensivmediziner",
    "address": "Lainzer Straße 131/1.Stock, 1130 Wien",
    "services": "",
    "photo_url": "https://assets.docfinder.at/frontend/images/static/avatars/doctor.svg",
    "gallery": null,
    "appointment_url": null,
    "search_slug": "neuropathologe",
    "phone": "+43 676 9730222",
    "fax": null,
    "email": null,
    "website": null,
    "description": "Neurologe, Neuropathologe, Intensivmediziner",
    "address_full": "Lainzer Straße 131/1.Stock",
    "zip_code": "1130",
    "city": "Wien",
    "opening_hours": {
      "Thursday": "16:00–19:00",
      "Tuesday": "16:00–19:00"
    },
    "latitude": "48.177562",
    "longitude": "16.284066",
    "photo_url_full": "https://assets.docfinder.at/frontend/images/static/avatars/doctor.svg"
  },
  {
    "name": "Univ.Prof. Dr. Gert Johann Mayer",
    "profile_url": "https://www.docfinder.at/internist/6020-innsbruck/dr-gert-johann-mayer",
    "rating": null,
    "reviews": null,
    "specialty": "Internist, Nephrologe",
    "address": "Anichstraße 35, 6020 Innsbruck",
    "services": "",
    "photo_url": "https://assets.docfinder.at/frontend/images/static/avatars/doctor.svg",
    "gallery": null,
    "appointment_url": null,
    "search_slug": "neuropathologe",
    "phone": "+43 512 504 258 55",
    "fax": null,
    "email": null,
    "website": null,
    "description": "Internist, Nephrologe",
    "address_full": "Anichstraße 35",
    "zip_code": "6020",
    "city": "Innsbruck",
    "opening_hours": null,
    "latitude": "47.262849",
    "longitude": "11.386422",
    "photo_url_full": "https://assets.docfinder.at/frontend/images/static/avatars/doctor.svg"
  },
  {
    "name": "OA Dr. Martin Lederer",
    "profile_url": "https://www.docfinder.at/internist/1190-wien/dr-martin-lederer",
    "rating": null,
    "reviews": null,
    "specialty": "Internist, Nephrologe",
    "address": "Hungerbergstraße 3-5/6/2, 1190 Wien",
    "services": "",
    "photo_url": "https://assets.docfinder.at/frontend/images/static/avatars/doctor.svg",
    "gallery": null,
    "appointment_url": null,
    "search_slug": "neuropathologe",
    "phone": "+43 664 643 29 80",
    "fax": null,
    "email": null,
    "website": null,
    "description": "Internist, Nephrologe",
    "address_full": "Hungerbergstraße 3-5/6/2",
    "zip_code": "1190",
    "city": "Wien",
    "opening_hours": null,
    "latitude": "48.250793",
    "longitude": "16.342482",
    "photo_url_full": "https://assets.docfinder.at/frontend/images/static/avatars/doctor.svg"
  },
  {
    "name": "Prim. Dr. Shadi Abu Daher",
    "profile_url": "https://www.docfinder.at/internist/1040-wien/dr-shadi-abu-daher",
    "rating": "4,87",
    "reviews": "50",
    "specialty": "Internist, Nephrologe",
    "address": "Wiedner Hauptstraße 56 / Top 1, 1040 Wien",
    "services": "",
    "photo_url": "https://images.docfinder.at/Hxzl5IfFX9/dr-shadi-abu-daher-internist-1040-wien-588c2.jpg",
    "gallery": null,
    "appointment_url": null,
    "search_slug": "neuropathologe",
    "phone": "+43 1   375 80 40",
    "fax": "01 / 375 80 40-50",
    "email": "office@internist-wieden.at",
    "website": "https://www.internist-wieden.at/",
    "description": "Internist, Nephrologe",
    "address_full": "Wiedner Hauptstraße 56 / Top 1",
    "zip_code": "1040",
    "city": "Wien",
    "opening_hours": {
      "Monday": "12:00–19:00",
      "Thursday": "07:00–11:00",
      "Tuesday": "09:00–16:00",
      "Wednesday": "09:00–15:00"
    },
    "latitude": "48.19929",
    "longitude": "16.36832",
    "photo_url_full": "https://images.docfinder.at/Hxzl5IfFX9/dr-shadi-abu-daher-internist-1040-wien-588c2.jpg"
  },
  {
    "name": "Univ.Prof. Dr. Martina Czerny-Franz",
    "profile_url": "https://www.docfinder.at/internist/3400-klosterneuburg/dr-martina-czerny-franz",
    "rating": "5,00",
    "reviews": "1",
    "specialty": "Internistin, Nephrologin",
    "address": "Bertholdgasse 2/2, 3400 Klosterneuburg",
    "services": "",
    "photo_url": "https://assets.docfinder.at/frontend/images/static/avatars/doctor_female.svg",
    "gallery": null,
    "appointment_url": null,
    "search_slug": "neuropathologe",
    "phone": "+43 2243 337 60",
    "fax": null,
    "email": null,
    "website": null,
    "description": "Internistin, Nephrologin",
    "address_full": "Bertholdgasse 2/2",
    "zip_code": "3400",
    "city": "Klosterneuburg",
    "opening_hours": null,
    "latitude": "48.296095",
    "longitude": "16.332833",
    "photo_url_full": "https://assets.docfinder.at/frontend/images/static/avatars/doctor_female.svg"
  },
  {
    "name": "Ao.Univ.Prof. Dr. Alice Ingrid Schmidt",
    "profile_url": "https://www.docfinder.at/internist/1090-wien/dr-alice-ingrid-schmidt",
    "rating": null,
    "reviews": null,
    "specialty": "Internistin, Nephrologin",
    "address": "Schwarzspanierstraße 15/1/11A, 1090 Wien",
    "services": "",
    "photo_url": "https://assets.docfinder.at/frontend/images/static/avatars/doctor_female.svg",
    "gallery": null,
    "appointment_url": null,
    "search_slug": "neuropathologe",
    "phone": "+43 1 406 36 88",
    "fax": null,
    "email": null,
    "website": null,
    "description": "Internistin, Nephrologin",
    "address_full": "Schwarzspanierstraße 15/1/11A",
    "zip_code": "1090",
    "city": "Wien",
    "opening_hours": {
      "Saturday": "09:00–13:00"
    },
    "latitude": "48.216758",
    "longitude": "16.357426",
    "photo_url_full": "https://assets.docfinder.at/frontend/images/static/avatars/doctor_female.svg"
  },
  {
    "name": "OÄ Dr. Miriam Stetter",
    "profile_url": "https://www.docfinder.at/internist/3300-amstetten/dr-miriam-stetter",
    "rating": "5,00",
    "reviews": "1",
    "specialty": "Internistin, Gastroenterologin u. Hepatologin, Nephrologin, Hämatologin u. Onkologin",
    "address": "Hauptplatz 17-19, 3300 Amstetten",
    "services": "",
    "photo_url": "https://assets.docfinder.at/frontend/images/static/avatars/doctor_female.svg",
    "gallery": null,
    "appointment_url": null,
    "search_slug": "neuropathologe",
    "phone": "+43 664 355 34 00",
    "fax": null,
    "email": null,
    "website": null,
    "description": "Internistin, Gastroenterologin u. Hepatologin, Nephrologin, Hämatologin u. Onkologin",
    "address_full": "Hauptplatz 17-19",
    "zip_code": "3300",
    "city": "Amstetten",
    "opening_hours": {
      "Tuesday": "18:30–20:00",
      "Wednesday": "16:30–20:00"
    },
    "latitude": "48.122723",
    "longitude": "14.872942",
    "photo_url_full": "https://assets.docfinder.at/frontend/images/static/avatars/doctor_female.svg"
  },
  {
    "name": "Dr. Renate Zach",
    "profile_url": "https://www.docfinder.at/internist/8010-graz/dr-renate-zach",
    "rating": null,
    "reviews": null,
    "specialty": "Internistin, Nephrologin",
    "address": "Opernring 6, 8010 Graz",
    "services": "",
    "photo_url": "https://assets.docfinder.at/frontend/images/static/avatars/doctor_female.svg",
    "gallery": null,
    "appointment_url": null,
    "search_slug": "neuropathologe",
    "phone": "+43 664   190 51 69",
    "fax": null,
    "email": null,
    "website": null,
    "description": "Internistin, Nephrologin",
    "address_full": "Opernring 6",
    "zip_code": "8010",
    "city": "Graz",
    "opening_hours": {
      "Friday": "08:00–13:00",
      "Monday": "14:00–19:00",
      "Thursday": "14:00–19:00",
      "Tuesday": "10:00–18:00",
      "Wednesday": "08:00–13:00"
    },
    "latitude": "47.07019",
    "longitude": "15.4452",
    "photo_url_full": "https://assets.docfinder.at/frontend/images/static/avatars/doctor_female.svg"
  },
  {
    "name": "OA Dr. Martin Jansen",
    "profile_url": "https://www.docfinder.at/internist/1020-wien/dr-martin-jansen",
    "rating": "5,00",
    "reviews": "2",
    "specialty": "Internist, Nephrologe",
    "address": "Zirkusgasse 5/6/4, 1020 Wien",
    "services": "",
    "photo_url": "https://assets.docfinder.at/frontend/images/static/avatars/doctor.svg",
    "gallery": null,
    "appointment_url": null,
    "search_slug": "neuropathologe",
    "phone": "+43 676 551 55 20",
    "fax": null,
    "email": null,
    "website": null,
    "description": "Internist, Nephrologe",
    "address_full": "Zirkusgasse 5/6/4",
    "zip_code": "1020",
    "city": "Wien",
    "opening_hours": null,
    "latitude": "48.214739",
    "longitude": "16.382783",
    "photo_url_full": "https://assets.docfinder.at/frontend/images/static/avatars/doctor.svg"
  },
  {
    "name": "Dr. Dorothea Heininger",
    "profile_url": "https://www.docfinder.at/internist/4810-gmunden/dr-dorothea-heininger",
    "rating": "5,00",
    "reviews": "3",
    "specialty": "Internistin, Nephrologin",
    "address": "Georgstraße 7/2.Stock, 4810 Gmunden",
    "services": "",
    "photo_url": "https://assets.docfinder.at/frontend/images/static/avatars/doctor_female.svg",
    "gallery": null,
    "appointment_url": null,
    "search_slug": "neuropathologe",
    "phone": "+43 676 756 50 14",
    "fax": null,
    "email": null,
    "website": null,
    "description": "Internistin, Nephrologin",
    "address_full": "Georgstraße 7/2.Stock",
    "zip_code": "4810",
    "city": "Gmunden",
    "opening_hours": {
      "Monday": "08:00–14:00",
      "Thursday": "08:00–14:00",
      "Tuesday": "13:00–17:30",
      "Wednesday": "08:00–18:00"
    },
    "latitude": "47.91832",
    "longitude": "13.80486",
    "photo_url_full": "https://assets.docfinder.at/frontend/images/static/avatars/doctor_female.svg"
  },
  {
    "name": "Prim. Ao.Univ.Prof. Dr. Renate Martina Klauser-Braun",
    "profile_url": "https://www.docfinder.at/internist/1080-wien/dr-renate-martina-klauser-braun",
    "rating": "5,00",
    "reviews": "3",
    "specialty": "Internistin, Nephrologin",
    "address": "Krotenthallergasse 3-5, 1080 Wien",
    "services": "",
    "photo_url": "https://assets.docfinder.at/frontend/images/static/avatars/doctor_female.svg",
    "gallery": null,
    "appointment_url": null,
    "search_slug": "neuropathologe",
    "phone": "+43 1 40 666 00",
    "fax": null,
    "email": null,
    "website": null,
    "description": "Internistin, Nephrologin",
    "address_full": "Krotenthallergasse 3-5",
    "zip_code": "1080",
    "city": "Wien",
    "opening_hours": {
      "Tuesday": "17:00–19:00"
    },
    "latitude": "48.2117",
    "longitude": "16.34617",
    "photo_url_full": "https://assets.docfinder.at/frontend/images/static/avatars/doctor_female.svg"
  },
  {
    "name": "Univ. Prof. Dr. Herbert Kopsa",
    "profile_url": "https://www.docfinder.at/internist/1090-wien/dr-herbert-kopsa",
    "rating": "5,00",
    "reviews": "5",
    "specialty": "Internist, Nephrologe",
    "address": "Berggasse 20/13, 1090 Wien",
    "services": "",
    "photo_url": "https://assets.docfinder.at/frontend/images/static/avatars/doctor.svg",
    "gallery": null,
    "appointment_url": null,
    "search_slug": "neuropathologe",
    "phone": "+43 1 317 92 81",
    "fax": null,
    "email": null,
    "website": null,
    "description": "Internist, Nephrologe",
    "address_full": "Berggasse 20/13",
    "zip_code": "1090",
    "city": "Wien",
    "opening_hours": {
      "Monday": "15:00–18:00",
      "Thursday": "15:00–18:00",
      "Tuesday": "15:00–18:00",
      "Wednesday": "15:00–18:00"
    },
    "latitude": "48.218451",
    "longitude": "16.363321",
    "photo_url_full": "https://assets.docfinder.at/frontend/images/static/avatars/doctor.svg"
  },
  {
    "name": "Dr. Rainer Huditz",
    "profile_url": "https://www.docfinder.at/internist/9020-klagenfurt/dr-rainer-huditz",
    "rating": "4,33",
    "reviews": "6",
    "specialty": "Internist, Nephrologe, Geriater",
    "address": "Getreidegasse 16, 9020 Klagenfurt",
    "services": "",
    "photo_url": "https://assets.docfinder.at/frontend/images/static/avatars/doctor.svg",
    "gallery": null,
    "appointment_url": null,
    "search_slug": "neuropathologe",
    "phone": "+43 463   511 367",
    "fax": null,
    "email": null,
    "website": null,
    "description": "Internist, Nephrologe, Geriater",
    "address_full": "Getreidegasse 16",
    "zip_code": "9020",
    "city": "Klagenfurt",
    "opening_hours": {
      "Friday": "08:00–10:00",
      "Monday": "08:00–14:00",
      "Thursday": "08:00–14:00",
      "Tuesday": "15:00–18:00",
      "Wednesday": "08:00–14:00"
    },
    "latitude": "46.62601",
    "longitude": "14.31189",
    "photo_url_full": "https://assets.docfinder.at/frontend/images/static/avatars/doctor.svg"
  },
  {
    "name": "Prim. Dr. Georg Galvan",
    "profile_url": "https://www.docfinder.at/internist/5400-hallein/dr-georg-galvan",
    "rating": "5,00",
    "reviews": "1",
    "specialty": "Internist, Nephrologe",
    "address": "Kuffergasse 9, 5400 Hallein",
    "services": "",
    "photo_url": "https://assets.docfinder.at/frontend/images/static/avatars/doctor.svg",
    "gallery": null,
    "appointment_url": null,
    "search_slug": "neuropathologe",
    "phone": "+43 6245 830 19",
    "fax": null,
    "email": null,
    "website": null,
    "description": "Internist, Nephrologe",
    "address_full": "Kuffergasse 9",
    "zip_code": "5400",
    "city": "Hallein",
    "opening_hours": {
      "Friday": "07:30–14:00",
      "Monday": "07:30–12:00, 15:00–17:00",
      "Thursday": "14:00–16:00, 08:00–12:00",
      "Tuesday": "14:00–18:00, 08:00–12:00",
      "Wednesday": "08:00–12:00, 14:00–18:00"
    },
    "latitude": "47.68293",
    "longitude": "13.09413",
    "photo_url_full": "https://assets.docfinder.at/frontend/images/static/avatars/doctor.svg"
  },
  {
    "name": "Univ.Prof. Dr. Josef Kovarik",
    "profile_url": "https://www.docfinder.at/internist/1080-wien/dr-josef-kovarik",
    "rating": "5,00",
    "reviews": "1",
    "specialty": "Internist, Nephrologe",
    "address": "Skodagasse 32, Ordinationszentrum Confraternität, 1080 Wien",
    "services": "",
    "photo_url": "https://assets.docfinder.at/frontend/images/static/avatars/doctor.svg",
    "gallery": null,
    "appointment_url": null,
    "search_slug": "neuropathologe",
    "phone": "+43 1 491 502 608",
    "fax": null,
    "email": null,
    "website": null,
    "description": "Internist, Nephrologe",
    "address_full": "Skodagasse 32, Ordinationszentrum Confraternität",
    "zip_code": "1080",
    "city": "Wien",
    "opening_hours": {
      "Tuesday": "16:00–19:00"
    },
    "latitude": "48.21004",
    "longitude": "16.347007",
    "photo_url_full": "https://assets.docfinder.at/frontend/images/static/avatars/doctor.svg"
  },
  {
    "name": "Dr. Roland Schaufler",
    "profile_url": "https://www.docfinder.at/internist/1150-wien/dr-roland-schaufler",
    "rating": "5,00",
    "reviews": "3",
    "specialty": "Internist, Nephrologe",
    "address": "Holochergasse 55/31, 1150 Wien",
    "services": "",
    "photo_url": "https://assets.docfinder.at/frontend/images/static/avatars/doctor.svg",
    "gallery": null,
    "appointment_url": null,
    "search_slug": "neuropathologe",
    "phone": "+43 678 1294346",
    "fax": null,
    "email": null,
    "website": null,
    "description": "Internist, Nephrologe",
    "address_full": "Holochergasse 55/31",
    "zip_code": "1150",
    "city": "Wien",
    "opening_hours": {
      "Friday": "08:30–15:00",
      "Monday": "08:30–15:00",
      "Thursday": "08:30–15:00",
      "Tuesday": "08:30–15:00",
      "Wednesday": "08:30–15:00"
    },
    "latitude": "48.200511",
    "longitude": "16.323985",
    "photo_url_full": "https://assets.docfinder.at/frontend/images/static/avatars/doctor.svg"
  },
  {
    "name": "OA Dr. Gernot Perz",
    "profile_url": "https://www.docfinder.at/internist/9500-villach/dr-gernot-perz",
    "rating": "3,93",
    "reviews": "3",
    "specialty": "Internist, Nephrologe, Endokrinologe, Gastroenterologe u. Hepatologe",
    "address": "Hans-Gasser-Platz 4, 9500 Villach",
    "services": "",
    "photo_url": "https://assets.docfinder.at/frontend/images/static/avatars/doctor.svg",
    "gallery": null,
    "appointment_url": null,
    "search_slug": "neuropathologe",
    "phone": "+43 4242 262 330",
    "fax": null,
    "email": null,
    "website": null,
    "description": "Internist, Nephrologe, Endokrinologe, Gastroenterologe u. Hepatologe",
    "address_full": "Hans-Gasser-Platz 4",
    "zip_code": "9500",
    "city": "Villach",
    "opening_hours": {
      "Friday": "08:00–14:00",
      "Monday": "08:00–14:00",
      "Thursday": "08:00–14:00",
      "Tuesday": "08:00–14:00",
      "Wednesday": "08:00–14:00"
    },
    "latitude": "46.6121884",
    "longitude": "13.8429882",
    "photo_url_full": "https://assets.docfinder.at/frontend/images/static/avatars/doctor.svg"
  },
  {
    "name": "Ao.Univ.Prof. Dr. Falko Skrabal",
    "profile_url": "https://www.docfinder.at/internist/8043-graz/dr-falko-skrabal",
    "rating": "4,33",
    "reviews": "6",
    "specialty": "Internist, Kardiologe, Endokrinologe, Nephrologe",
    "address": "Mariatroster Straße 67, 8043 Graz",
    "services": "",
    "photo_url": "https://assets.docfinder.at/frontend/images/static/avatars/doctor.svg",
    "gallery": null,
    "appointment_url": null,
    "search_slug": "neuropathologe",
    "phone": "+43 316 67 67 67",
    "fax": null,
    "email": null,
    "website": null,
    "description": "Internist, Kardiologe, Endokrinologe, Nephrologe",
    "address_full": "Mariatroster Straße 67",
    "zip_code": "8043",
    "city": "Graz",
    "opening_hours": {
      "Thursday": "09:00–13:00",
      "Tuesday": "09:00–13:00"
    },
    "latitude": "47.093757",
    "longitude": "15.462029",
    "photo_url_full": "https://assets.docfinder.at/frontend/images/static/avatars/doctor.svg"
  },
  {
    "name": "Dr. Angelina Mischek",
    "profile_url": "https://www.docfinder.at/internist/1090-wien/dr-angelina-mischek",
    "rating": "5,00",
    "reviews": "8",
    "specialty": "Internistin, Nephrologin",
    "address": "Grünentorgasse 19A/4, 1090 Wien",
    "services": "",
    "photo_url": "https://assets.docfinder.at/frontend/images/static/avatars/doctor_female.svg",
    "gallery": null,
    "appointment_url": null,
    "search_slug": "neuropathologe",
    "phone": "+43 680 238 53 93",
    "fax": null,
    "email": null,
    "website": null,
    "description": "Internistin, Nephrologin",
    "address_full": "Grünentorgasse 19A/4",
    "zip_code": "1090",
    "city": "Wien",
    "opening_hours": null,
    "latitude": "48.22099",
    "longitude": "16.36378",
    "photo_url_full": "https://assets.docfinder.at/frontend/images/static/avatars/doctor_female.svg"
  },
  {
    "name": "Dr. Rainer Hubmann",
    "profile_url": "https://www.docfinder.at/internist/4040-linz/dr-rainer-hubmann",
    "rating": "4,41",
    "reviews": "59",
    "specialty": "Internist, Gastroenterologe u. Hepatologe, Nephrologe",
    "address": "Hauptstraße 54, 4040 Linz",
    "services": "",
    "photo_url": "https://assets.docfinder.at/frontend/images/static/avatars/doctor.svg",
    "gallery": null,
    "appointment_url": null,
    "search_slug": "neuropathologe",
    "phone": "+43 732 733 000",
    "fax": null,
    "email": null,
    "website": null,
    "description": "Internist, Gastroenterologe u. Hepatologe, Nephrologe",
    "address_full": "Hauptstraße 54",
    "zip_code": "4040",
    "city": "Linz",
    "opening_hours": {
      "Friday": "08:00–11:30",
      "Monday": "08:00–11:30",
      "Thursday": "08:00–11:30, 15:00–17:00",
      "Tuesday": "16:00–20:00",
      "Wednesday": "08:00–11:30"
    },
    "latitude": "48.314036",
    "longitude": "14.281488",
    "photo_url_full": "https://assets.docfinder.at/frontend/images/static/avatars/doctor.svg"
  },
  {
    "name": "Prof. Dr. Gürkan Sengölge",
    "profile_url": "https://www.docfinder.at/internist/1080-wien/dr-guerkan-sengoelge",
    "rating": "4,97",
    "reviews": "31",
    "specialty": "Internist, Nephrologe",
    "address": "Lange Gasse 67/9, 1080 Wien",
    "services": "Systemerkrankungen mit Nierenbeteiligung; Proteinurie (Eiweiß im Harn); Ödeme; Nierenerkrankungen; Hämaturie (Blut im Harn); Hypertonie",
    "photo_url": "https://images.docfinder.at/Np2LObM0kD/dr-guerkan-sengoelge-internist-1080-wien-4aab.jpg",
    "gallery": [
      "https://images.docfinder.at/Np2LObM0kD/praxis-dr-guerkan-sengoelge-internist-1080-wien-53850.jpg",
      "https://images.docfinder.at/Np2LObM0kD/praxis-dr-guerkan-sengoelge-internist-1080-wien-33346.jpg",
      "https://images.docfinder.at/Np2LObM0kD/praxis-dr-guerkan-sengoelge-internist-1080-wien-6c53b.jpg"
    ],
    "appointment_url": null,
    "search_slug": "neuropathologe",
    "phone": "+43 1 4020585",
    "fax": null,
    "email": "info@co-ordination.at",
    "website": "https://www.co-ordination.at/",
    "description": "Internist, Nephrologe",
    "address_full": "Lange Gasse 67/9",
    "zip_code": "1080",
    "city": "Wien",
    "opening_hours": null,
    "latitude": "48.214455",
    "longitude": "16.350821",
    "photo_url_full": "https://images.docfinder.at/Np2LObM0kD/dr-guerkan-sengoelge-internist-1080-wien-4aab.jpg"
  },
  {
    "name": "OÄ Dr. med. univ. Danielle Diarra",
    "profile_url": "https://www.docfinder.at/internist/1070-wien/dr-danielle-diarra",
    "rating": "5,00",
    "reviews": "9",
    "specialty": "Internistin, Nephrologin",
    "address": "Zieglergasse 39/3 , 1070 Wien",
    "services": "",
    "photo_url": "https://images.docfinder.at/c3vbw13wZA/oae-dr-med-univ-danielle-diarra-677-7.jpg",
    "gallery": null,
    "appointment_url": null,
    "search_slug": "neuropathologe",
    "phone": "+43 1  394 88 88",
    "fax": null,
    "email": null,
    "website": "https://www.ordination-neubau.at/",
    "description": "Internistin, Nephrologin",
    "address_full": "Zieglergasse 39/3 ",
    "zip_code": "1070",
    "city": "Wien",
    "opening_hours": {
      "Friday": "15:00–18:00",
      "Monday": "08:00–13:00",
      "Thursday": "09:30–14:00",
      "Tuesday": "08:00–13:00",
      "Wednesday": "12:00–13:30"
    },
    "latitude": "48.20247",
    "longitude": "16.34485",
    "photo_url_full": "https://images.docfinder.at/c3vbw13wZA/oae-dr-med-univ-danielle-diarra-677-7.jpg"
  },
  {
    "name": "Univ.Doz. Dr. Irmgard Neumann",
    "profile_url": "https://www.docfinder.at/internist/1010-wien/dr-irmgard-neumann",
    "rating": "4,20",
    "reviews": "5",
    "specialty": "Internistin, Nephrologin, Nuklearmedizinerin",
    "address": "Eßlinggasse 18/17, 1010 Wien",
    "services": "",
    "photo_url": "https://assets.docfinder.at/frontend/images/static/avatars/doctor_female.svg",
    "gallery": null,
    "appointment_url": null,
    "search_slug": "neuropathologe",
    "phone": "+43 664 738 75 011",
    "fax": null,
    "email": null,
    "website": null,
    "description": "Internistin, Nephrologin, Nuklearmedizinerin",
    "address_full": "Eßlinggasse 18/17",
    "zip_code": "1010",
    "city": "Wien",
    "opening_hours": null,
    "latitude": "48.216027",
    "longitude": "16.37082",
    "photo_url_full": "https://assets.docfinder.at/frontend/images/static/avatars/doctor_female.svg"
  },
  {
    "name": "OA Dr. Walter Manker",
    "profile_url": "https://www.docfinder.at/internist/1190-wien/dr-walter-manker",
    "rating": null,
    "reviews": null,
    "specialty": "Internist, Nephrologe",
    "address": "Heiligenstädter Straße 113/3, 1190 Wien",
    "services": "",
    "photo_url": "https://assets.docfinder.at/frontend/images/static/avatars/doctor.svg",
    "gallery": null,
    "appointment_url": null,
    "search_slug": "neuropathologe",
    "phone": "+43 1 367 62 66",
    "fax": null,
    "email": null,
    "website": null,
    "description": "Internist, Nephrologe",
    "address_full": "Heiligenstädter Straße 113/3",
    "zip_code": "1190",
    "city": "Wien",
    "opening_hours": {
      "Monday": "15:00–19:00",
      "Thursday": "09:00–12:00, 15:00–18:00",
      "Tuesday": "09:00–12:00, 15:00–19:00",
      "Wednesday": "09:00–12:00"
    },
    "latitude": "48.248314",
    "longitude": "16.362149",
    "photo_url_full": "https://assets.docfinder.at/frontend/images/static/avatars/doctor.svg"
  },
  {
    "name": "Dr. Alfred Hager",
    "profile_url": "https://www.docfinder.at/internist/2500-baden/dr-alfred-hager",
    "rating": "5,00",
    "reviews": "5",
    "specialty": "Internist, Nephrologe",
    "address": "Palffygasse 2, 2500 Baden",
    "services": "",
    "photo_url": "https://assets.docfinder.at/frontend/images/static/avatars/doctor.svg",
    "gallery": null,
    "appointment_url": null,
    "search_slug": "neuropathologe",
    "phone": "+43 664   1628766",
    "fax": null,
    "email": null,
    "website": null,
    "description": "Internist, Nephrologe",
    "address_full": "Palffygasse 2",
    "zip_code": "2500",
    "city": "Baden",
    "opening_hours": {
      "Tuesday": "15:00–19:00"
    },
    "latitude": "48.005436",
    "longitude": "16.243177",
    "photo_url_full": "https://assets.docfinder.at/frontend/images/static/avatars/doctor.svg"
  },
  {
    "name": "OA Dr. Johann Grüssing",
    "profile_url": "https://www.docfinder.at/internist/5020-salzburg/dr-johann-gruessing",
    "rating": "4,36",
    "reviews": "5",
    "specialty": "Internist, Nephrologe",
    "address": "Elisabethstraße 1a, 5020 Salzburg",
    "services": "",
    "photo_url": "https://assets.docfinder.at/frontend/images/static/avatars/doctor.svg",
    "gallery": null,
    "appointment_url": null,
    "search_slug": "neuropathologe",
    "phone": "+43 662 874 900",
    "fax": null,
    "email": null,
    "website": null,
    "description": "Internist, Nephrologe",
    "address_full": "Elisabethstraße 1a",
    "zip_code": "5020",
    "city": "Salzburg",
    "opening_hours": {
      "Monday": "07:30–13:00",
      "Thursday": "07:30–13:00",
      "Tuesday": "07:30–13:00, 15:00–17:00"
    },
    "latitude": "47.809979",
    "longitude": "13.041623",
    "photo_url_full": "https://assets.docfinder.at/frontend/images/static/avatars/doctor.svg"
  },
  {
    "name": "OA Dr. Lothar Riedlinger",
    "profile_url": "https://www.docfinder.at/internist/1030-wien/dr-lothar-riedlinger",
    "rating": "3,00",
    "reviews": "4",
    "specialty": "Internist, Nephrologe",
    "address": "Hintzerstraße 10/6, 1030 Wien",
    "services": "",
    "photo_url": "https://assets.docfinder.at/frontend/images/static/avatars/doctor.svg",
    "gallery": null,
    "appointment_url": null,
    "search_slug": "neuropathologe",
    "phone": "+43 1 7103826",
    "fax": null,
    "email": null,
    "website": null,
    "description": "Internist, Nephrologe",
    "address_full": "Hintzerstraße 10/6",
    "zip_code": "1030",
    "city": "Wien",
    "opening_hours": {
      "Wednesday": "14:00–18:00"
    },
    "latitude": "48.200304",
    "longitude": "16.390717",
    "photo_url_full": "https://assets.docfinder.at/frontend/images/static/avatars/doctor.svg"
  },
  {
    "name": "Univ.Prof. Dr. Alexander Rosenkranz",
    "profile_url": "https://www.docfinder.at/internist/8036-graz/dr-alexander-rosenkranz",
    "rating": null,
    "reviews": null,
    "specialty": "Internist, Nephrologe",
    "address": "Auenbruggerplatz 27/III, 8036 Graz",
    "services": "",
    "photo_url": "https://assets.docfinder.at/frontend/images/static/avatars/doctor.svg",
    "gallery": null,
    "appointment_url": null,
    "search_slug": "neuropathologe",
    "phone": "+43 316 12170",
    "fax": null,
    "email": null,
    "website": null,
    "description": "Internist, Nephrologe",
    "address_full": "Auenbruggerplatz 27/III",
    "zip_code": "8036",
    "city": "Graz",
    "opening_hours": null,
    "latitude": "47.081161",
    "longitude": "15.463724",
    "photo_url_full": "https://assets.docfinder.at/frontend/images/static/avatars/doctor.svg"
  },
  {
    "name": "Dr. Julia Hofmann",
    "profile_url": "https://www.docfinder.at/internist/5083-hallein/dr-julia-hofmann",
    "rating": null,
    "reviews": null,
    "specialty": "Internistin, Nephrologin",
    "address": "Kupfergasse 9, 5083 Hallein",
    "services": "",
    "photo_url": "https://assets.docfinder.at/frontend/images/static/avatars/doctor_female.svg",
    "gallery": null,
    "appointment_url": null,
    "search_slug": "neuropathologe",
    "phone": "+43 699 110 85 811",
    "fax": null,
    "email": null,
    "website": null,
    "description": "Internistin, Nephrologin",
    "address_full": "Kupfergasse 9",
    "zip_code": "5083",
    "city": "Hallein",
    "opening_hours": null,
    "latitude": "47.68293",
    "longitude": "13.09413",
    "photo_url_full": "https://assets.docfinder.at/frontend/images/static/avatars/doctor_female.svg"
  },
  {
    "name": "OA Dr. Arnold Panzenböck",
    "profile_url": "https://www.docfinder.at/internist/4020-linz/dr-arnold-panzenboeck",
    "rating": "5,00",
    "reviews": "5",
    "specialty": "Internist, Nephrologe",
    "address": "Landstraße 35b, 4020 Linz",
    "services": "",
    "photo_url": "https://assets.docfinder.at/frontend/images/static/avatars/doctor.svg",
    "gallery": null,
    "appointment_url": null,
    "search_slug": "neuropathologe",
    "phone": "+43 732 77 80 89",
    "fax": null,
    "email": null,
    "website": null,
    "description": "Internist, Nephrologe",
    "address_full": "Landstraße 35b",
    "zip_code": "4020",
    "city": "Linz",
    "opening_hours": {
      "Friday": "07:30–12:00, 13:00–15:00",
      "Monday": "07:30–12:00, 13:00–17:00",
      "Thursday": "07:30–12:00, 13:00–17:00",
      "Tuesday": "07:30–13:00, 14:00–17:00",
      "Wednesday": "07:30–12:00, 13:00–17:00"
    },
    "latitude": "48.30144",
    "longitude": "14.290497",
    "photo_url_full": "https://assets.docfinder.at/frontend/images/static/avatars/doctor.svg"
  },
  {
    "name": "Dr. med. Neda Khalifeh",
    "profile_url": "https://www.docfinder.at/internist/1010-wien/dr-neda-khalifeh",
    "rating": "5,00",
    "reviews": "257",
    "specialty": "Internistin, Nephrologin",
    "address": "Franz-Josefs-Kai 65/2-4, 1010 Wien",
    "services": "Neben der ausführlichen Anamnese wird die modernste Diagnostik für die Erkennung und Vorbeugung von Herz-Kreislauferkrankungen eingesetzt. Was wir für Sie machen können:",
    "photo_url": "https://images.docfinder.at/KhBCDmdlGu/dr-med-neda-khalifeh-7396e.jpg",
    "gallery": null,
    "appointment_url": null,
    "search_slug": "neuropathologe",
    "phone": "+43 699 120 035 88",
    "fax": null,
    "email": "welcome@healthfirst.at",
    "website": "https://www.healthfirst.at",
    "description": "Internistin, Nephrologin",
    "address_full": "Franz-Josefs-Kai 65/2-4",
    "zip_code": "1010",
    "city": "Wien",
    "opening_hours": {
      "Monday": "09:00–15:30",
      "Thursday": "10:00–18:00",
      "Tuesday": "09:00–17:00",
      "Wednesday": "09:00–15:00"
    },
    "latitude": "48.21787",
    "longitude": "16.36948",
    "photo_url_full": "https://images.docfinder.at/KhBCDmdlGu/dr-med-neda-khalifeh-7396e.jpg"
  },
  {
    "name": "Prim. Univ.Doz. Dr. Karl Lhotta",
    "profile_url": "https://www.docfinder.at/internist/6800-feldkirch/dr-karl-lhotta",
    "rating": null,
    "reviews": null,
    "specialty": "Internist, Nephrologe",
    "address": "Carinagasse 45, 6800 Feldkirch",
    "services": "",
    "photo_url": "https://assets.docfinder.at/frontend/images/static/avatars/doctor.svg",
    "gallery": null,
    "appointment_url": null,
    "search_slug": "neuropathologe",
    "phone": "+43 5522 3030",
    "fax": null,
    "email": null,
    "website": null,
    "description": "Internist, Nephrologe",
    "address_full": "Carinagasse 45",
    "zip_code": "6800",
    "city": "Feldkirch",
    "opening_hours": null,
    "latitude": "47.230155",
    "longitude": "9.580818",
    "photo_url_full": "https://assets.docfinder.at/frontend/images/static/avatars/doctor.svg"
  },
  {
    "name": "OA Dr. Peter Slawitsch",
    "profile_url": "https://www.docfinder.at/internist/8055-graz-puntigam/dr-peter-slawitsch",
    "rating": "3,11",
    "reviews": "9",
    "specialty": "Internist, Nephrologe, Gastroenterologe u. Hepatologe",
    "address": "Brauquartier 1/Top 12, 8055 Graz-Puntigam",
    "services": "",
    "photo_url": "https://assets.docfinder.at/frontend/images/static/avatars/doctor.svg",
    "gallery": null,
    "appointment_url": null,
    "search_slug": "neuropathologe",
    "phone": "+43 316 243 814",
    "fax": null,
    "email": null,
    "website": null,
    "description": "Internist, Nephrologe, Gastroenterologe u. Hepatologe",
    "address_full": "Brauquartier 1/Top 12",
    "zip_code": "8055",
    "city": "Graz-Puntigam",
    "opening_hours": {
      "Wednesday": "17:00–19:00"
    },
    "latitude": "47.03284",
    "longitude": "15.43192",
    "photo_url_full": "https://assets.docfinder.at/frontend/images/static/avatars/doctor.svg"
  }
]